async_typer/__init__.py
async_typer/async_typer.py
async_typer-0.1.10.dist-info/METADATA
async_typer-0.1.10.dist-info/WHEEL
async_typer-0.1.10.dist-info/RECORD
