Metadata-Version: 2.1
Name: async-typer
Version: 0.1.10
Summary: A simple async wrapper for typer
Author: byunjuneseok
Author-email: byunjuneseok@gmail.com
Requires-Python: >=3.10,<4.0
Classifier: Development Status :: 5 - Production/Stable
Classifier: Intended Audience :: Developers
Classifier: Operating System :: OS Independent
Classifier: Programming Language :: Python
Classifier: Programming Language :: Python :: 3
Classifier: Programming Language :: Python :: 3.10
Classifier: Programming Language :: Python :: 3.11
Classifier: Programming Language :: Python :: 3.12
Classifier: Programming Language :: Python :: 3.13
Classifier: Programming Language :: Python :: Implementation :: PyPy
Requires-Dist: typer (>=0.9.0,<1.0.0)
Project-URL: Bug Tracker, https://github.com/byunjuneseok/async-typer/issues
Project-URL: homepage, https://github.com/byunjuneseok/async-typer
Project-URL: repository, https://github.com/byunjuneseok/async-typer
